Metadata-Version: 2.1
Name: mpcspy
Version: 0.0.4
Summary: My Personal Configuration System for Python
Home-page: https://github.com/goktug97/mpcspy
Author: Göktuğ Karakaşlı
Author-email: karakasligk@gmail.com
License: MIT
Download-URL: https://github.com/goktug97/mpcspy/archive/v0.0.4.tar.gz
Platform: UNKNOWN
Classifier: Programming Language :: Python :: 3
Classifier: License :: OSI Approved :: MIT License
Requires-Python: >=3.6
